Metadata-Version: 2.1
Name: PyHal
Version: 10.2.6
Summary: Your swiss knife to perform fast and easy pythonic stuff
Home-page: https://sirfoga.github.io/pyhal/
Author: Stefano Fogarollo
Author-email: sirfoga@protonmail.com
License: UNKNOWN
Keywords: hal library general-purpose
Platform: UNKNOWN
